{
    "@schema": "https://raw.githubusercontent.com/slicer/slicer/master/Modules/Loadable/Markups/Resources/Schema/markups-schema-v1.0.3.json#",
    "markups": [
        {
            "type": "Fiducial",
            "coordinateSystem": "LPS",
            "coordinateUnits": "mm",
            "locked": false,
            "fixedNumberOfControlPoints": false,
            "labelFormat": "%N-%d",
            "lastUsedControlPointNumber": 138,
            "controlPoints": [
                {
                    "id": "1",
                    "label": "PseudoLandmarks-1",
                    "description": "Semi",
                    "associatedNodeID": "",
                    "position": [-0.5419177727230514, -4.168420944352081, -7.970938021203746],
                    "orientation": [-1.0, -0.0, -0.0, -0.0, -1.0, -0.0, 0.0, 0.0, 1.0],
                    "selected": true,
                    "locked": true,
                    "visibility": true,
                    "positionStatus": "defined"
                },
                {
                    "id": "2",
                    "label": "PseudoLandmarks-2",
                    "description": "Semi",
                    "associatedNodeID": "",
                    "position": [-0.7788958744533981, -4.4978963471841125, -7.951035982629527],
                    "orientation": [-1.0, -0.0, -0.0, -0.0, -1.0, -0.0, 0.0, 0.0, 1.0],
                    "selected": true,
                    "locked": true,
                    "visibility": true,
                    "positionStatus": "defined"
                },
                {
                    "id": "3",
                    "label": "PseudoLandmarks-3",
                    "description": "Semi",
                    "associatedNodeID": "",
                    "position": [-0.634015436602446, -4.3771581269692685, -7.954006868859996],
                    "orientation": [-1.0, -0.0, -0.0, -0.0, -1.0, -0.0, 0.0, 0.0, 1.0],
                    "selected": true,
                    "locked": true,
                    "visibility": true,
                    "positionStatus": "defined"
                },
                {
                    "id": "4",
                    "label": "PseudoLandmarks-4",
                    "description": "Semi",
                    "associatedNodeID": "",
                    "position": [-0.8569150642879928, -4.332963714737823, -7.946350008508434],
                    "orientation": [-1.0, -0.0, -0.0, -0.0, -1.0, -0.0, 0.0, 0.0, 1.0],
                    "selected": true,
                    "locked": true,
                    "visibility": true,
                    "positionStatus": "defined"
                },
                {
                    "id": "5",
                    "label": "PseudoLandmarks-5",
                    "description": "Semi",
                    "associatedNodeID": "",
                    "position": [-0.721085806322905, -4.205272827286652, -7.958372408410777],
                    "orientation": [-1.0, -0.0, -0.0, -0.0, -1.0, -0.0, 0.0, 0.0, 1.0],
                    "selected": true,
                    "locked": true,
                    "visibility": true,
                    "positionStatus": "defined"
                },
                {
                    "id": "6",
                    "label": "PseudoLandmarks-6",
                    "description": "Semi",
                    "associatedNodeID": "",
                    "position": [-0.364573069048735, -4.127315292496612, -7.946369081994762],
                    "orientation": [-1.0, -0.0, -0.0, -0.0, -1.0, -0.0, 0.0, 0.0, 1.0],
                    "selected": true,
                    "locked": true,
                    "visibility": true,
                    "positionStatus": "defined"
                },
                {
                    "id": "7",
                    "label": "PseudoLandmarks-7",
                    "description": "Semi",
                    "associatedNodeID": "",
                    "position": [-0.6957795814999069, -4.017335281510284, -7.949204927942027],
                    "orientation": [-1.0, -0.0, -0.0, -0.0, -1.0, -0.0, 0.0, 0.0, 1.0],
                    "selected": true,
                    "locked": true,
                    "visibility": true,
                    "positionStatus": "defined"
                },
                {
                    "id": "8",
                    "label": "PseudoLandmarks-8",
                    "description": "Semi",
                    "associatedNodeID": "",
                    "position": [-0.5087363438137497, -3.9904460526894834, -7.956100374719371],
                    "orientation": [-1.0, -0.0, -0.0, -0.0, -1.0, -0.0, 0.0, 0.0, 1.0],
                    "selected": true,
                    "locked": true,
                    "visibility": true,
                    "positionStatus": "defined"
                },
                {
                    "id": "9",
                    "label": "PseudoLandmarks-9",
                    "description": "Semi",
                    "associatedNodeID": "",
                    "position": [-0.9651961998470748, -4.517330322403839, -7.924915224572887],
                    "orientation": [-1.0, -0.0, -0.0, -0.0, -1.0, -0.0, 0.0, 0.0, 1.0],
                    "selected": true,
                    "locked": true,
                    "visibility": true,
                    "positionStatus": "defined"
                },
                {
                    "id": "10",
                    "label": "PseudoLandmarks-10",
                    "description": "Semi",
                    "associatedNodeID": "",
                    "position": [-0.45378975434384, -4.404948196549347, -7.924999910852184],
                    "orientation": [-1.0, -0.0, -0.0, -0.0, -1.0, -0.0, 0.0, 0.0, 1.0],
                    "selected": true,
                    "locked": true,
                    "visibility": true,
                    "positionStatus": "defined"
                },
                {
                    "id": "11",
                    "label": "PseudoLandmarks-11",
                    "description": "Semi",
                    "associatedNodeID": "",
                    "position": [-0.9254776672848192, -4.158058700699737, -7.925566774865855],
                    "orientation": [-1.0, -0.0, -0.0, -0.0, -1.0, -0.0, 0.0, 0.0, 1.0],
                    "selected": true,
                    "locked": true,
                    "visibility": true,
                    "positionStatus": "defined"
                },
                {
                    "id": "12",
                    "label": "PseudoLandmarks-12",
                    "description": "Semi",
                    "associatedNodeID": "",
                    "position": [-0.84603988690457, -4.675801239151886, -7.909847170373668],
                    "orientation": [-1.0, -0.0, -0.0, -0.0, -1.0, -0.0, 0.0, 0.0, 1.0],
                    "selected": true,
                    "locked": true,
                    "visibility": true,
                    "positionStatus": "defined"
                },
                {
                    "id": "13",
                    "label": "PseudoLandmarks-13",
                    "description": "Semi",
                    "associatedNodeID": "",
                    "position": [-0.6600039200314011, -4.671628723282745, -7.904273134729136],
                    "orientation": [-1.0, -0.0, -0.0, -0.0, -1.0, -0.0, 0.0, 0.0, 1.0],
                    "selected": true,
                    "locked": true,
                    "visibility": true,
                    "positionStatus": "defined"
                },
                {
                    "id": "14",
                    "label": "PseudoLandmarks-14",
                    "description": "Semi",
                    "associatedNodeID": "",
                    "position": [-1.09304015202603, -4.387621078629425, -7.902060610315074],
                    "orientation": [-1.0, -0.0, -0.0, -0.0, -1.0, -0.0, 0.0, 0.0, 1.0],
                    "selected": true,
                    "locked": true,
                    "visibility": true,
                    "positionStatus": "defined"
                },
                {
                    "id": "15",
                    "label": "PseudoLandmarks-15",
                    "description": "Semi",
                    "associatedNodeID": "",
                    "position": [-0.29510244889340054, -4.300263366837433, -7.905547243615855],
                    "orientation": [-1.0, -0.0, -0.0, -0.0, -1.0, -0.0, 0.0, 0.0, 1.0],
                    "selected": true,
                    "locked": true,
                    "visibility": true,
                    "positionStatus": "defined"
                },
                {
                    "id": "16",
                    "label": "PseudoLandmarks-16",
                    "description": "Semi",
                    "associatedNodeID": "",
                    "position": [-1.1043734268673389, -4.201770935196808, -7.908813387414684],
                    "orientation": [-1.0, -0.0, -0.0, -0.0, -1.0, -0.0, 0.0, 0.0, 1.0],
                    "selected": true,
                    "locked": true,
                    "visibility": true,
                    "positionStatus": "defined"
                },
                {
                    "id": "17",
                    "label": "PseudoLandmarks-17",
                    "description": "Semi",
                    "associatedNodeID": "",
                    "position": [-1.052108068896147, -4.0269233323525695, -7.904610353967418],
                    "orientation": [-1.0, -0.0, -0.0, -0.0, -1.0, -0.0, 0.0, 0.0, 1.0],
                    "selected": true,
                    "locked": true,
                    "visibility": true,
                    "positionStatus": "defined"
                },
                {
                    "id": "18",
                    "label": "PseudoLandmarks-18",
                    "description": "Semi",
                    "associatedNodeID": "",
                    "position": [-0.8790882305630172, -3.959845314164093, -7.9042388024537455],
                    "orientation": [-1.0, -0.0, -0.0, -0.0, -1.0, -0.0, 0.0, 0.0, 1.0],
                    "selected": true,
                    "locked": true,
                    "visibility": true,
                    "positionStatus": "defined"
                },
                {
                    "id": "19",
                    "label": "PseudoLandmarks-19",
                    "description": "Semi",
                    "associatedNodeID": "",
                    "position": [-0.3382549957760299, -3.9484609223794247, -7.90532141353773],
                    "orientation": [-1.0, -0.0, -0.0, -0.0, -1.0, -0.0, 0.0, 0.0, 1.0],
                    "selected": true,
                    "locked": true,
                    "visibility": true,
                    "positionStatus": "defined"
                },
                {
                    "id": "20",
                    "label": "PseudoLandmarks-20",
                    "description": "Semi",
                    "associatedNodeID": "",
                    "position": [-0.684581728411528, -3.8319970704507136, -7.902957064172496],
                    "orientation": [-1.0, -0.0, -0.0, -0.0, -1.0, -0.0, 0.0, 0.0, 1.0],
                    "selected": true,
                    "locked": true,
                    "visibility": true,
                    "positionStatus": "defined"
                },
                {
                    "id": "21",
                    "label": "PseudoLandmarks-21",
                    "description": "Semi",
                    "associatedNodeID": "",
                    "position": [-0.4880720333584274, -3.8214566804360657, -7.889683443567027],
                    "orientation": [-1.0, -0.0, -0.0, -0.0, -1.0, -0.0, 0.0, 0.0, 1.0],
                    "selected": true,
                    "locked": true,
                    "visibility": true,
                    "positionStatus": "defined"
                },
                {
                    "id": "22",
                    "label": "PseudoLandmarks-22",
                    "description": "Semi",
                    "associatedNodeID": "",
                    "position": [-0.4958061890133346, -4.575821457047393, -7.8654006066529645],
                    "orientation": [-1.0, -0.0, -0.0, -0.0, -1.0, -0.0, 0.0, 0.0, 1.0],
                    "selected": true,
                    "locked": true,
                    "visibility": true,
                    "positionStatus": "defined"
                },
                {
                    "id": "23",
                    "label": "PseudoLandmarks-23",
                    "description": "Semi",
                    "associatedNodeID": "",
                    "position": [-0.1896689669617141, -4.147327575821808, -7.861113268396129],
                    "orientation": [-1.0, -0.0, -0.0, -0.0, -1.0, -0.0, 0.0, 0.0, 1.0],
                    "selected": true,
                    "locked": true,
                    "visibility": true,
                    "positionStatus": "defined"
                },
                {
                    "id": "24",
                    "label": "PseudoLandmarks-24",
                    "description": "Semi",
                    "associatedNodeID": "",
                    "position": [-1.228227396441313, -4.069038925309112, -7.860663515588511],
                    "orientation": [-1.0, -0.0, -0.0, -0.0, -1.0, -0.0, 0.0, 0.0, 1.0],
                    "selected": true,
                    "locked": true,
                    "visibility": true,
                    "positionStatus": "defined"
                },
                {
                    "id": "25",
                    "label": "PseudoLandmarks-25",
                    "description": "Semi",
                    "associatedNodeID": "",
                    "position": [-1.022460146380278, -4.700999221939972, -7.843375307580699],
                    "orientation": [-1.0, -0.0, -0.0, -0.0, -1.0, -0.0, 0.0, 0.0, 1.0],
                    "selected": true,
                    "locked": true,
                    "visibility": true,
                    "positionStatus": "defined"
                },
                {
                    "id": "26",
                    "label": "PseudoLandmarks-26",
                    "description": "Semi",
                    "associatedNodeID": "",
                    "position": [-0.3209182338245834, -4.531342849869659, -7.837411028405894],
                    "orientation": [-1.0, -0.0, -0.0, -0.0, -1.0, -0.0, 0.0, 0.0, 1.0],
                    "selected": true,
                    "locked": true,
                    "visibility": true,
                    "positionStatus": "defined"
                },
                {
                    "id": "27",
                    "label": "PseudoLandmarks-27",
                    "description": "Semi",
                    "associatedNodeID": "",
                    "position": [-1.2458195404537644, -4.289119873185089, -7.83623190548109],
                    "orientation": [-1.0, -0.0, -0.0, -0.0, -1.0, -0.0, 0.0, 0.0, 1.0],
                    "selected": true,
                    "locked": true,
                    "visibility": true,
                    "positionStatus": "defined"
                },
                {
                    "id": "28",
                    "label": "PseudoLandmarks-28",
                    "description": "Semi",
                    "associatedNodeID": "",
                    "position": [-1.081678839159819, -3.86041656507962, -7.837809282800426],
                    "orientation": [-1.0, -0.0, -0.0, -0.0, -1.0, -0.0, 0.0, 0.0, 1.0],
                    "selected": true,
                    "locked": true,
                    "visibility": true,
                    "positionStatus": "defined"
                },
                {
                    "id": "29",
                    "label": "PseudoLandmarks-29",
                    "description": "Semi",
                    "associatedNodeID": "",
                    "position": [-0.8730616764553513, -3.7880624391030575, -7.834295565149058],
                    "orientation": [-1.0, -0.0, -0.0, -0.0, -1.0, -0.0, 0.0, 0.0, 1.0],
                    "selected": true,
                    "locked": true,
                    "visibility": true,
                    "positionStatus": "defined"
                },
                {
                    "id": "30",
                    "label": "PseudoLandmarks-30",
                    "description": "Semi",
                    "associatedNodeID": "",
                    "position": [-0.7910801605709519, -4.824085006852081, -7.818984896203746],
                    "orientation": [-1.0, -0.0, -0.0, -0.0, -1.0, -0.0, 0.0, 0.0, 1.0],
                    "selected": true,
                    "locked": true,
                    "visibility": true,
                    "positionStatus": "defined"
                },
                {
                    "id": "31",
                    "label": "PseudoLandmarks-31",
                    "description": "Semi",
                    "associatedNodeID": "",
                    "position": [-1.1593005852230513, -4.570939407486846, -7.814439302942027],
                    "orientation": [-1.0, -0.0, -0.0, -0.0, -1.0, -0.0, 0.0, 0.0, 1.0],
                    "selected": true,
                    "locked": true,
                    "visibility": true,
                    "positionStatus": "defined"
                },
                {
                    "id": "32",
                    "label": "PseudoLandmarks-32",
                    "description": "Semi",
                    "associatedNodeID": "",
                    "position": [-0.1647028641231979, -3.968720779557159, -7.818698030969371],
                    "orientation": [-1.0, -0.0, -0.0, -0.0, -1.0, -0.0, 0.0, 0.0, 1.0],
                    "selected": true,
                    "locked": true,
                    "visibility": true,
                    "positionStatus": "defined"
                },
                {
                    "id": "33",
                    "label": "PseudoLandmarks-33",
                    "description": "Semi",
                    "associatedNodeID": "",
                    "position": [-0.17333515150627743, -4.41500869764798, -7.811468416711558],
                    "orientation": [-1.0, -0.0, -0.0, -0.0, -1.0, -0.0, 0.0, 0.0, 1.0],
                    "selected": true,
                    "locked": true,
                    "visibility": true,
                    "positionStatus": "defined"
                },
                {
                    "id": "34",
                    "label": "PseudoLandmarks-34",
                    "description": "Semi",
                    "associatedNodeID": "",
                    "position": [-0.2747440175541366, -3.8142743684243463, -7.796953112146129],
                    "orientation": [-1.0, -0.0, -0.0, -0.0, -1.0, -0.0, 0.0, 0.0, 1.0],
                    "selected": true,
                    "locked": true,
                    "visibility": true,
                    "positionStatus": "defined"
                },
                {
                    "id": "35",
                    "label": "PseudoLandmarks-35",
                    "description": "Semi",
                    "associatedNodeID": "",
                    "position": [-0.6125831799038376, -4.801810226578644, -7.7836028161256205],
                    "orientation": [-1.0, -0.0, -0.0, -0.0, -1.0, -0.0, 0.0, 0.0, 1.0],
                    "selected": true,
                    "locked": true,
                    "visibility": true,
                    "positionStatus": "defined"
                },
                {
                    "id": "36",
                    "label": "PseudoLandmarks-36",
                    "description": "Semi",
                    "associatedNodeID": "",
                    "position": [-1.245172186327788, -3.900109062333038, -7.7681010308473],
                    "orientation": [-1.0, -0.0, -0.0, -0.0, -1.0, -0.0, 0.0, 0.0, 1.0],
                    "selected": true,
                    "locked": true,
                    "visibility": true,
                    "positionStatus": "defined"
                },
                {
                    "id": "37",
                    "label": "PseudoLandmarks-37",
                    "description": "Semi",
                    "associatedNodeID": "",
                    "position": [-0.6923465446957077, -3.7052486039590145, -7.770394808313121],
                    "orientation": [-1.0, -0.0, -0.0, -0.0, -1.0, -0.0, 0.0, 0.0, 1.0],
                    "selected": true,
                    "locked": true,
                    "visibility": true,
                    "positionStatus": "defined"
                },
                {
                    "id": "38",
                    "label": "PseudoLandmarks-38",
                    "description": "Semi",
                    "associatedNodeID": "",
                    "position": [-0.07138740582546843, -4.26191574110501, -7.762467485925425],
                    "orientation": [-1.0, -0.0, -0.0, -0.0, -1.0, -0.0, 0.0, 0.0, 1.0],
                    "selected": true,
                    "locked": true,
                    "visibility": true,
                    "positionStatus": "defined"
                },
                {
                    "id": "39",
                    "label": "PseudoLandmarks-39",
                    "description": "Semi",
                    "associatedNodeID": "",
                    "position": [-0.9557778076656784, -4.837526092667511, -7.727682787439098],
                    "orientation": [-1.0, -0.0, -0.0, -0.0, -1.0, -0.0, 0.0, 0.0, 1.0],
                    "selected": true,
                    "locked": true,
                    "visibility": true,
                    "positionStatus": "defined"
                },
                {
                    "id": "40",
                    "label": "PseudoLandmarks-40",
                    "description": "Semi",
                    "associatedNodeID": "",
                    "position": [-0.4772479729183639, -4.692657241959503, -7.725798708459605],
                    "orientation": [-1.0, -0.0, -0.0, -0.0, -1.0, -0.0, 0.0, 0.0, 1.0],
                    "selected": true,
                    "locked": true,
                    "visibility": true,
                    "positionStatus": "defined"
                },
                {
                    "id": "41",
                    "label": "PseudoLandmarks-41",
                    "description": "Semi",
                    "associatedNodeID": "",
                    "position": [-1.28168122334561, -4.446131286759307, -7.737032610437145],
                    "orientation": [-1.0, -0.0, -0.0, -0.0, -1.0, -0.0, 0.0, 0.0, 1.0],
                    "selected": true,
                    "locked": true,
                    "visibility": true,
                    "positionStatus": "defined"
                },
                {
                    "id": "42",
                    "label": "PseudoLandmarks-42",
                    "description": "Semi",
                    "associatedNodeID": "",
                    "position": [-1.3440053658016649, -4.151992950577667, -7.73925924923109],
                    "orientation": [-1.0, -0.0, -0.0, -0.0, -1.0, -0.0, 0.0, 0.0, 1.0],
                    "selected": true,
                    "locked": true,
                    "visibility": true,
                    "positionStatus": "defined"
                },
                {
                    "id": "43",
                    "label": "PseudoLandmarks-43",
                    "description": "Semi",
                    "associatedNodeID": "",
                    "position": [-0.03948080105862273, -4.082159958023956, -7.737750917932262],
                    "orientation": [-1.0, -0.0, -0.0, -0.0, -1.0, -0.0, 0.0, 0.0, 1.0],
                    "selected": true,
                    "locked": true,
                    "visibility": true,
                    "positionStatus": "defined"
                },
                {
                    "id": "44",
                    "label": "PseudoLandmarks-44",
                    "description": "Semi",
                    "associatedNodeID": "",
                    "position": [-0.5035031036861861, -3.7155450440835263, -7.729820925256481],
                    "orientation": [-1.0, -0.0, -0.0, -0.0, -1.0, -0.0, 0.0, 0.0, 1.0],
                    "selected": true,
                    "locked": true,
                    "visibility": true,
                    "positionStatus": "defined"
                },
                {
                    "id": "45",
                    "label": "PseudoLandmarks-45",
                    "description": "Semi",
                    "associatedNodeID": "",
                    "position": [-0.19960708780369407, -4.571772155899932, -7.707300859948863],
                    "orientation": [-1.0, -0.0, -0.0, -0.0, -1.0, -0.0, 0.0, 0.0, 1.0],
                    "selected": true,
                    "locked": true,
                    "visibility": true,
                    "positionStatus": "defined"
                },
                {
                    "id": "46",
                    "label": "PseudoLandmarks-46",
                    "description": "Semi",
                    "associatedNodeID": "",
                    "position": [-1.1340226845272507, -4.716907272477081, -7.7014704766480815],
                    "orientation": [-1.0, -0.0, -0.0, -0.0, -1.0, -0.0, 0.0, 0.0, 1.0],
                    "selected": true,
                    "locked": true,
                    "visibility": true,
                    "positionStatus": "defined"
                },
                {
                    "id": "47",
                    "label": "PseudoLandmarks-47",
                    "description": "Semi",
                    "associatedNodeID": "",
                    "position": [-0.10371918393454203, -3.858994445938995, -7.686944109460582],
                    "orientation": [-1.0, -0.0, -0.0, -0.0, -1.0, -0.0, 0.0, 0.0, 1.0],
                    "selected": true,
                    "locked": true,
                    "visibility": true,
                    "positionStatus": "defined"
                },
                {
                    "id": "48",
                    "label": "PseudoLandmarks-48",
                    "description": "Semi",
                    "associatedNodeID": "",
                    "position": [-1.002390451861235, -3.7840318299721982, -7.687383181115855],
                    "orientation": [-1.0, -0.0, -0.0, -0.0, -1.0, -0.0, 0.0, 0.0, 1.0],
                    "selected": true,
                    "locked": true,
                    "visibility": true,
                    "positionStatus": "defined"
                },
                {
                    "id": "49",
                    "label": "PseudoLandmarks-49",
                    "description": "Semi",
                    "associatedNodeID": "",
                    "position": [-0.7231190399654831, -4.911741409439972, -7.655202394983043],
                    "orientation": [-1.0, -0.0, -0.0, -0.0, -1.0, -0.0, 0.0, 0.0, 1.0],
                    "selected": true,
                    "locked": true,
                    "visibility": true,
                    "positionStatus": "defined"
                },
                {
                    "id": "50",
                    "label": "PseudoLandmarks-50",
                    "description": "Semi",
                    "associatedNodeID": "",
                    "position": [-0.06369543833813318, -4.445503006119659, -7.6621932091920275],
                    "orientation": [-1.0, -0.0, -0.0, -0.0, -1.0, -0.0, 0.0, 0.0, 1.0],
                    "selected": true,
                    "locked": true,
                    "visibility": true,
                    "positionStatus": "defined"
                },
                {
                    "id": "51",
                    "label": "PseudoLandmarks-51",
                    "description": "Semi",
                    "associatedNodeID": "",
                    "position": [-0.8263399796017136, -3.749645958084991, -7.65217428829359],
                    "orientation": [-1.0, -0.0, -0.0, -0.0, -1.0, -0.0, 0.0, 0.0, 1.0],
                    "selected": true,
                    "locked": true,
                    "visibility": true,
                    "positionStatus": "defined"
                },
                {
                    "id": "52",
                    "label": "PseudoLandmarks-52",
                    "description": "Semi",
                    "associatedNodeID": "",
                    "position": [-0.3457244829662765, -3.732628212113312, -7.635128695031871],
                    "orientation": [-1.0, -0.0, -0.0, -0.0, -1.0, -0.0, 0.0, 0.0, 1.0],
                    "selected": true,
                    "locked": true,
                    "visibility": true,
                    "positionStatus": "defined"
                },
                {
                    "id": "53",
                    "label": "PseudoLandmarks-53",
                    "description": "Semi",
                    "associatedNodeID": "",
                    "position": [-1.2537339882381882, -4.597063598771026, -7.622509295007457],
                    "orientation": [-1.0, -0.0, -0.0, -0.0, -1.0, -0.0, 0.0, 0.0, 1.0],
                    "selected": true,
                    "locked": true,
                    "visibility": true,
                    "positionStatus": "defined"
                },
                {
                    "id": "54",
                    "label": "PseudoLandmarks-54",
                    "description": "Semi",
                    "associatedNodeID": "",
                    "position": [-0.3878160671719039, -4.5647145844888, -7.616393953820934],
                    "orientation": [-1.0, -0.0, -0.0, -0.0, -1.0, -0.0, 0.0, 0.0, 1.0],
                    "selected": true,
                    "locked": true,
                    "visibility": true,
                    "positionStatus": "defined"
                },
                {
                    "id": "55",
                    "label": "PseudoLandmarks-55",
                    "description": "Semi",
                    "associatedNodeID": "",
                    "position": [-1.3548214630611861, -4.30960975660794, -7.625809771081675],
                    "orientation": [-1.0, -0.0, -0.0, -0.0, -1.0, -0.0, 0.0, 0.0, 1.0],
                    "selected": true,
                    "locked": true,
                    "visibility": true,
                    "positionStatus": "defined"
                },
                {
                    "id": "56",
                    "label": "PseudoLandmarks-56",
                    "description": "Semi",
                    "associatedNodeID": "",
                    "position": [-1.3114267067440477, -4.014041290421416, -7.620883089563121],
                    "orientation": [-1.0, -0.0, -0.0, -0.0, -1.0, -0.0, 0.0, 0.0, 1.0],
                    "selected": true,
                    "locked": true,
                    "visibility": true,
                    "positionStatus": "defined"
                },
                {
                    "id": "57",
                    "label": "PseudoLandmarks-57",
                    "description": "Semi",
                    "associatedNodeID": "",
                    "position": [-0.5587726788052048, -4.822551117081573, -7.604597383996715],
                    "orientation": [-1.0, -0.0, -0.0, -0.0, -1.0, -0.0, 0.0, 0.0, 1.0],
                    "selected": true,
                    "locked": true,
                    "visibility": true,
                    "positionStatus": "defined"
                },
                {
                    "id": "58",
                    "label": "PseudoLandmarks-58",
                    "description": "Semi",
                    "associatedNodeID": "",
                    "position": [0.01940734820285195, -4.292809066910674, -7.597842699548473],
                    "orientation": [-1.0, -0.0, -0.0, -0.0, -1.0, -0.0, 0.0, 0.0, 1.0],
                    "selected": true,
                    "locked": true,
                    "visibility": true,
                    "positionStatus": "defined"
                },
                {
                    "id": "59",
                    "label": "PseudoLandmarks-59",
                    "description": "Semi",
                    "associatedNodeID": "",
                    "position": [0.03782614903369297, -3.998248062272003, -7.593517214318981],
                    "orientation": [-1.0, -0.0, -0.0, -0.0, -1.0, -0.0, 0.0, 0.0, 1.0],
                    "selected": true,
                    "locked": true,
                    "visibility": true,
                    "positionStatus": "defined"
                },
                {
                    "id": "60",
                    "label": "PseudoLandmarks-60",
                    "description": "Semi",
                    "associatedNodeID": "",
                    "position": [-1.176343317461821, -3.871685180802276, -7.602314669152965],
                    "orientation": [-1.0, -0.0, -0.0, -0.0, -1.0, -0.0, 0.0, 0.0, 1.0],
                    "selected": true,
                    "locked": true,
                    "visibility": true,
                    "positionStatus": "defined"
                },
                {
                    "id": "61",
                    "label": "PseudoLandmarks-61",
                    "description": "Semi",
                    "associatedNodeID": "",
                    "position": [-0.6363123135097946, -3.7404550172280575, -7.600348955651988],
                    "orientation": [-1.0, -0.0, -0.0, -0.0, -1.0, -0.0, 0.0, 0.0, 1.0],
                    "selected": true,
                    "locked": true,
                    "visibility": true,
                    "positionStatus": "defined"
                },
                {
                    "id": "62",
                    "label": "PseudoLandmarks-62",
                    "description": "Semi",
                    "associatedNodeID": "",
                    "position": [-0.9117314533718552, -4.882451019425323, -7.550164705774058],
                    "orientation": [-1.0, -0.0, -0.0, -0.0, -1.0, -0.0, 0.0, 0.0, 1.0],
                    "selected": true,
                    "locked": true,
                    "visibility": true,
                    "positionStatus": "defined"
                },
                {
                    "id": "63",
                    "label": "PseudoLandmarks-63",
                    "description": "Semi",
                    "associatedNodeID": "",
                    "position": [-1.0855525688656296, -4.800037918229034, -7.534852129480113],
                    "orientation": [-1.0, -0.0, -0.0, -0.0, -1.0, -0.0, 0.0, 0.0, 1.0],
                    "selected": true,
                    "locked": true,
                    "visibility": true,
                    "positionStatus": "defined"
                },
                {
                    "id": "64",
                    "label": "PseudoLandmarks-64",
                    "description": "Semi",
                    "associatedNodeID": "",
                    "position": [-0.158743550015303, -4.537769851822784, -7.527949816247691],
                    "orientation": [-1.0, -0.0, -0.0, -0.0, -1.0, -0.0, 0.0, 0.0, 1.0],
                    "selected": true,
                    "locked": true,
                    "visibility": true,
                    "positionStatus": "defined"
                },
                {
                    "id": "65",
                    "label": "PseudoLandmarks-65",
                    "description": "Semi",
                    "associatedNodeID": "",
                    "position": [-0.1814302103050674, -3.780411873001983, -7.525796419641246],
                    "orientation": [-1.0, -0.0, -0.0, -0.0, -1.0, -0.0, 0.0, 0.0, 1.0],
                    "selected": true,
                    "locked": true,
                    "visibility": true,
                    "positionStatus": "defined"
                },
                {
                    "id": "66",
                    "label": "PseudoLandmarks-66",
                    "description": "Semi",
                    "associatedNodeID": "",
                    "position": [-0.5065521435268844, -4.6649701692055965, -7.516663271447887],
                    "orientation": [-1.0, -0.0, -0.0, -0.0, -1.0, -0.0, 0.0, 0.0, 1.0],
                    "selected": true,
                    "locked": true,
                    "visibility": true,
                    "positionStatus": "defined"
                },
                {
                    "id": "67",
                    "label": "PseudoLandmarks-67",
                    "description": "Semi",
                    "associatedNodeID": "",
                    "position": [-1.322437353564116, -4.454287872452666, -7.512109285852183],
                    "orientation": [-1.0, -0.0, -0.0, -0.0, -1.0, -0.0, 0.0, 0.0, 1.0],
                    "selected": true,
                    "locked": true,
                    "visibility": true,
                    "positionStatus": "defined"
                },
                {
                    "id": "68",
                    "label": "PseudoLandmarks-68",
                    "description": "Semi",
                    "associatedNodeID": "",
                    "position": [-1.0239768700130905, -3.840634880204131, -7.508750444909801],
                    "orientation": [-1.0, -0.0, -0.0, -0.0, -1.0, -0.0, 0.0, 0.0, 1.0],
                    "selected": true,
                    "locked": true,
                    "visibility": true,
                    "positionStatus": "defined"
                },
                {
                    "id": "69",
                    "label": "PseudoLandmarks-69",
                    "description": "Semi",
                    "associatedNodeID": "",
                    "position": [-0.4831206039913619, -3.776757011551788, -7.508148867151012],
                    "orientation": [-1.0, -0.0, -0.0, -0.0, -1.0, -0.0, 0.0, 0.0, 1.0],
                    "selected": true,
                    "locked": true,
                    "visibility": true,
                    "positionStatus": "defined"
                },
                {
                    "id": "70",
                    "label": "PseudoLandmarks-70",
                    "description": "Semi",
                    "associatedNodeID": "",
                    "position": [-1.3257622437008347, -4.175195083756377, -7.502514177819957],
                    "orientation": [-1.0, -0.0, -0.0, -0.0, -1.0, -0.0, 0.0, 0.0, 1.0],
                    "selected": true,
                    "locked": true,
                    "visibility": true,
                    "positionStatus": "defined"
                },
                {
                    "id": "71",
                    "label": "PseudoLandmarks-71",
                    "description": "Semi",
                    "associatedNodeID": "",
                    "position": [0.08562162356295933, -4.14945465101712, -7.486638552209605],
                    "orientation": [-1.0, -0.0, -0.0, -0.0, -1.0, -0.0, 0.0, 0.0, 1.0],
                    "selected": true,
                    "locked": true,
                    "visibility": true,
                    "positionStatus": "defined"
                },
                {
                    "id": "72",
                    "label": "PseudoLandmarks-72",
                    "description": "Semi",
                    "associatedNodeID": "",
                    "position": [-0.7404373363979782, -4.910053024430206, -7.471226793786753],
                    "orientation": [-1.0, -0.0, -0.0, -0.0, -1.0, -0.0, 0.0, 0.0, 1.0],
                    "selected": true,
                    "locked": true,
                    "visibility": true,
                    "positionStatus": "defined"
                },
                {
                    "id": "73",
                    "label": "PseudoLandmarks-73",
                    "description": "Semi",
                    "associatedNodeID": "",
                    "position": [-0.021219881010862696, -4.419172439713409, -7.471911150476207],
                    "orientation": [-1.0, -0.0, -0.0, -0.0, -1.0, -0.0, 0.0, 0.0, 1.0],
                    "selected": true,
                    "locked": true,
                    "visibility": true,
                    "positionStatus": "defined"
                },
                {
                    "id": "74",
                    "label": "PseudoLandmarks-74",
                    "description": "Semi",
                    "associatedNodeID": "",
                    "position": [-1.2130758003719773, -3.9919654466103816, -7.467551714441051],
                    "orientation": [-1.0, -0.0, -0.0, -0.0, -1.0, -0.0, 0.0, 0.0, 1.0],
                    "selected": true,
                    "locked": true,
                    "visibility": true,
                    "positionStatus": "defined"
                },
                {
                    "id": "75",
                    "label": "PseudoLandmarks-75",
                    "description": "Semi",
                    "associatedNodeID": "",
                    "position": [-0.02740727229199058, -3.8684268571328424, -7.465855700036753],
                    "orientation": [-1.0, -0.0, -0.0, -0.0, -1.0, -0.0, 0.0, 0.0, 1.0],
                    "selected": true,
                    "locked": true,
                    "visibility": true,
                    "positionStatus": "defined"
                },
                {
                    "id": "76",
                    "label": "PseudoLandmarks-76",
                    "description": "Semi",
                    "associatedNodeID": "",
                    "position": [-0.8275126652248825, -3.8232282258462216, -7.467632204553356],
                    "orientation": [-1.0, -0.0, -0.0, -0.0, -1.0, -0.0, 0.0, 0.0, 1.0],
                    "selected": true,
                    "locked": true,
                    "visibility": true,
                    "positionStatus": "defined"
                },
                {
                    "id": "77",
                    "label": "PseudoLandmarks-77",
                    "description": "Semi",
                    "associatedNodeID": "",
                    "position": [-1.199774237109038, -4.658876571793488, -7.459250933191051],
                    "orientation": [-1.0, -0.0, -0.0, -0.0, -1.0, -0.0, 0.0, 0.0, 1.0],
                    "selected": true,
                    "locked": true,
                    "visibility": true,
                    "positionStatus": "defined"
                },
                {
                    "id": "78",
                    "label": "PseudoLandmarks-78",
                    "description": "Semi",
                    "associatedNodeID": "",
                    "position": [-0.3668317512997116, -4.500755844254424, -7.447164064904918],
                    "orientation": [-1.0, -0.0, -0.0, -0.0, -1.0, -0.0, 0.0, 0.0, 1.0],
                    "selected": true,
                    "locked": true,
                    "visibility": true,
                    "positionStatus": "defined"
                },
                {
                    "id": "79",
                    "label": "PseudoLandmarks-79",
                    "description": "Semi",
                    "associatedNodeID": "",
                    "position": [-0.6545139030941451, -4.753352508683135, -7.415259844323863],
                    "orientation": [-1.0, -0.0, -0.0, -0.0, -1.0, -0.0, 0.0, 0.0, 1.0],
                    "selected": true,
                    "locked": true,
                    "visibility": true,
                    "positionStatus": "defined"
                },
                {
                    "id": "80",
                    "label": "PseudoLandmarks-80",
                    "description": "Semi",
                    "associatedNodeID": "",
                    "position": [-0.6415528015621628, -3.830182228226593, -7.40952292110609],
                    "orientation": [-1.0, -0.0, -0.0, -0.0, -1.0, -0.0, 0.0, 0.0, 1.0],
                    "selected": true,
                    "locked": true,
                    "visibility": true,
                    "positionStatus": "defined"
                },
                {
                    "id": "81",
                    "label": "PseudoLandmarks-81",
                    "description": "Semi",
                    "associatedNodeID": "",
                    "position": [-0.9790152267940964, -4.823079071183136, -7.383718019983043],
                    "orientation": [-1.0, -0.0, -0.0, -0.0, -1.0, -0.0, 0.0, 0.0, 1.0],
                    "selected": true,
                    "locked": true,
                    "visibility": true,
                    "positionStatus": "defined"
                },
                {
                    "id": "82",
                    "label": "PseudoLandmarks-82",
                    "description": "Semi",
                    "associatedNodeID": "",
                    "position": [-1.3062808708675828, -4.321551284928253, -7.389070040246715],
                    "orientation": [-1.0, -0.0, -0.0, -0.0, -1.0, -0.0, 0.0, 0.0, 1.0],
                    "selected": true,
                    "locked": true,
                    "visibility": true,
                    "positionStatus": "defined"
                },
                {
                    "id": "83",
                    "label": "PseudoLandmarks-83",
                    "description": "Semi",
                    "associatedNodeID": "",
                    "position": [-0.35636298222622526, -3.8268395997475886, -7.385059649011363],
                    "orientation": [-1.0, -0.0, -0.0, -0.0, -1.0, -0.0, 0.0, 0.0, 1.0],
                    "selected": true,
                    "locked": true,
                    "visibility": true,
                    "positionStatus": "defined"
                },
                {
                    "id": "84",
                    "label": "PseudoLandmarks-84",
                    "description": "Semi",
                    "associatedNodeID": "",
                    "position": [-0.2416202382572616, -4.598762283463409, -7.354044252893199],
                    "orientation": [-1.0, -0.0, -0.0, -0.0, -1.0, -0.0, 0.0, 0.0, 1.0],
                    "selected": true,
                    "locked": true,
                    "visibility": true,
                    "positionStatus": "defined"
                },
                {
                    "id": "85",
                    "label": "PseudoLandmarks-85",
                    "description": "Semi",
                    "associatedNodeID": "",
                    "position": [-0.06341627998432764, -4.552735672135284, -7.356747728845347],
                    "orientation": [-1.0, -0.0, -0.0, -0.0, -1.0, -0.0, 0.0, 0.0, 1.0],
                    "selected": true,
                    "locked": true,
                    "visibility": true,
                    "positionStatus": "defined"
                },
                {
                    "id": "86",
                    "label": "PseudoLandmarks-86",
                    "description": "Semi",
                    "associatedNodeID": "",
                    "position": [0.04377755360522617, -4.276398620743683, -7.362434298059215],
                    "orientation": [-1.0, -0.0, -0.0, -0.0, -1.0, -0.0, 0.0, 0.0, 1.0],
                    "selected": true,
                    "locked": true,
                    "visibility": true,
                    "positionStatus": "defined"
                },
                {
                    "id": "87",
                    "label": "PseudoLandmarks-87",
                    "description": "Semi",
                    "associatedNodeID": "",
                    "position": [0.0670894427768266, -4.0077531434487605, -7.365928942224254],
                    "orientation": [-1.0, -0.0, -0.0, -0.0, -1.0, -0.0, 0.0, 0.0, 1.0],
                    "selected": true,
                    "locked": true,
                    "visibility": true,
                    "positionStatus": "defined"
                },
                {
                    "id": "88",
                    "label": "PseudoLandmarks-88",
                    "description": "Semi",
                    "associatedNodeID": "",
                    "position": [-1.0702308372982468, -3.951108131546905, -7.359397417566051],
                    "orientation": [-1.0, -0.0, -0.0, -0.0, -1.0, -0.0, 0.0, 0.0, 1.0],
                    "selected": true,
                    "locked": true,
                    "visibility": true,
                    "positionStatus": "defined"
                },
                {
                    "id": "89",
                    "label": "PseudoLandmarks-89",
                    "description": "Semi",
                    "associatedNodeID": "",
                    "position": [-0.5132576422222579, -4.661168823380401, -7.331703478357066],
                    "orientation": [-1.0, -0.0, -0.0, -0.0, -1.0, -0.0, 0.0, 0.0, 1.0],
                    "selected": true,
                    "locked": true,
                    "visibility": true,
                    "positionStatus": "defined"
                },
                {
                    "id": "90",
                    "label": "PseudoLandmarks-90",
                    "description": "Semi",
                    "associatedNodeID": "",
                    "position": [-1.251655931902739, -4.507648239273956, -7.33893080379652],
                    "orientation": [-1.0, -0.0, -0.0, -0.0, -1.0, -0.0, 0.0, 0.0, 1.0],
                    "selected": true,
                    "locked": true,
                    "visibility": true,
                    "positionStatus": "defined"
                },
                {
                    "id": "91",
                    "label": "PseudoLandmarks-91",
                    "description": "Semi",
                    "associatedNodeID": "",
                    "position": [-1.232866354418608, -4.16294227613919, -7.337729555627574],
                    "orientation": [-1.0, -0.0, -0.0, -0.0, -1.0, -0.0, 0.0, 0.0, 1.0],
                    "selected": true,
                    "locked": true,
                    "visibility": true,
                    "positionStatus": "defined"
                },
                {
                    "id": "92",
                    "label": "PseudoLandmarks-92",
                    "description": "Semi",
                    "associatedNodeID": "",
                    "position": [-0.1788211779125656, -3.845023689408233, -7.338144213220348],
                    "orientation": [-1.0, -0.0, -0.0, -0.0, -1.0, -0.0, 0.0, 0.0, 1.0],
                    "selected": true,
                    "locked": true,
                    "visibility": true,
                    "positionStatus": "defined"
                },
                {
                    "id": "93",
                    "label": "PseudoLandmarks-93",
                    "description": "Semi",
                    "associatedNodeID": "",
                    "position": [-0.873154612017485, -3.913015136856964, -7.315974718591441],
                    "orientation": [-1.0, -0.0, -0.0, -0.0, -1.0, -0.0, 0.0, 0.0, 1.0],
                    "selected": true,
                    "locked": true,
                    "visibility": true,
                    "positionStatus": "defined"
                },
                {
                    "id": "94",
                    "label": "PseudoLandmarks-94",
                    "description": "Semi",
                    "associatedNodeID": "",
                    "position": [-0.8030689911373581, -4.845076522965362, -7.297952944299449],
                    "orientation": [-1.0, -0.0, -0.0, -0.0, -1.0, -0.0, 0.0, 0.0, 1.0],
                    "selected": true,
                    "locked": true,
                    "visibility": true,
                    "positionStatus": "defined"
                },
                {
                    "id": "95",
                    "label": "PseudoLandmarks-95",
                    "description": "Semi",
                    "associatedNodeID": "",
                    "position": [-1.0841171936520064, -4.69382720961087, -7.302682405969371],
                    "orientation": [-1.0, -0.0, -0.0, -0.0, -1.0, -0.0, 0.0, 0.0, 1.0],
                    "selected": true,
                    "locked": true,
                    "visibility": true,
                    "positionStatus": "defined"
                },
                {
                    "id": "96",
                    "label": "PseudoLandmarks-96",
                    "description": "Semi",
                    "associatedNodeID": "",
                    "position": [-0.5046728090771163, -3.889107284684112, -7.295441347619762],
                    "orientation": [-1.0, -0.0, -0.0, -0.0, -1.0, -0.0, 0.0, 0.0, 1.0],
                    "selected": true,
                    "locked": true,
                    "visibility": true,
                    "positionStatus": "defined"
                },
                {
                    "id": "97",
                    "label": "PseudoLandmarks-97",
                    "description": "Semi",
                    "associatedNodeID": "",
                    "position": [-0.05636503262600545, -4.398760757584503, -7.2490771355836285],
                    "orientation": [-1.0, -0.0, -0.0, -0.0, -1.0, -0.0, 0.0, 0.0, 1.0],
                    "selected": true,
                    "locked": true,
                    "visibility": true,
                    "positionStatus": "defined"
                },
                {
                    "id": "98",
                    "label": "PseudoLandmarks-98",
                    "description": "Semi",
                    "associatedNodeID": "",
                    "position": [-0.6854518608578171, -3.9386176682900698, -7.260478502771129],
                    "orientation": [-1.0, -0.0, -0.0, -0.0, -1.0, -0.0, 0.0, 0.0, 1.0],
                    "selected": true,
                    "locked": true,
                    "visibility": true,
                    "positionStatus": "defined"
                },
                {
                    "id": "99",
                    "label": "PseudoLandmarks-99",
                    "description": "Semi",
                    "associatedNodeID": "",
                    "position": [-0.6492075161465133, -4.764117584366729, -7.229479891320933],
                    "orientation": [-1.0, -0.0, -0.0, -0.0, -1.0, -0.0, 0.0, 0.0, 1.0],
                    "selected": true,
                    "locked": true,
                    "visibility": true,
                    "positionStatus": "defined"
                },
                {
                    "id": "100",
                    "label": "PseudoLandmarks-100",
                    "description": "Semi",
                    "associatedNodeID": "",
                    "position": [-1.2127620415218796, -4.319150695938995, -7.2257826867310895],
                    "orientation": [-1.0, -0.0, -0.0, -0.0, -1.0, -0.0, 0.0, 0.0, 1.0],
                    "selected": true,
                    "locked": true,
                    "visibility": true,
                    "positionStatus": "defined"
                },
                {
                    "id": "101",
                    "label": "PseudoLandmarks-101",
                    "description": "Semi",
                    "associatedNodeID": "",
                    "position": [-1.089967699480864, -4.089207992691924, -7.236168581506481],
                    "orientation": [-1.0, -0.0, -0.0, -0.0, -1.0, -0.0, 0.0, 0.0, 1.0],
                    "selected": true,
                    "locked": true,
                    "visibility": true,
                    "positionStatus": "defined"
                },
                {
                    "id": "102",
                    "label": "PseudoLandmarks-102",
                    "description": "Semi",
                    "associatedNodeID": "",
                    "position": [-0.04045902652821187, -3.937720451493194, -7.236102587243785],
                    "orientation": [-1.0, -0.0, -0.0, -0.0, -1.0, -0.0, 0.0, 0.0, 1.0],
                    "selected": true,
                    "locked": true,
                    "visibility": true,
                    "positionStatus": "defined"
                },
                {
                    "id": "103",
                    "label": "PseudoLandmarks-103",
                    "description": "Semi",
                    "associatedNodeID": "",
                    "position": [-0.9295672134884324, -4.725581512589385, -7.209395891687144],
                    "orientation": [-1.0, -0.0, -0.0, -0.0, -1.0, -0.0, 0.0, 0.0, 1.0],
                    "selected": true,
                    "locked": true,
                    "visibility": true,
                    "positionStatus": "defined"
                },
                {
                    "id": "104",
                    "label": "PseudoLandmarks-104",
                    "description": "Semi",
                    "associatedNodeID": "",
                    "position": [-0.3760889486797775, -4.605819473404815, -7.2123133721558945],
                    "orientation": [-1.0, -0.0, -0.0, -0.0, -1.0, -0.0, 0.0, 0.0, 1.0],
                    "selected": true,
                    "locked": true,
                    "visibility": true,
                    "positionStatus": "defined"
                },
                {
                    "id": "105",
                    "label": "PseudoLandmarks-105",
                    "description": "Semi",
                    "associatedNodeID": "",
                    "position": [-1.1269414619930709, -4.53628555311673, -7.209720903894175],
                    "orientation": [-1.0, -0.0, -0.0, -0.0, -1.0, -0.0, 0.0, 0.0, 1.0],
                    "selected": true,
                    "locked": true,
                    "visibility": true,
                    "positionStatus": "defined"
                },
                {
                    "id": "106",
                    "label": "PseudoLandmarks-106",
                    "description": "Semi",
                    "associatedNodeID": "",
                    "position": [0.051618818806794864, -4.164675293106964, -7.207303911706676],
                    "orientation": [-1.0, -0.0, -0.0, -0.0, -1.0, -0.0, 0.0, 0.0, 1.0],
                    "selected": true,
                    "locked": true,
                    "visibility": true,
                    "positionStatus": "defined"
                },
                {
                    "id": "107",
                    "label": "PseudoLandmarks-107",
                    "description": "Semi",
                    "associatedNodeID": "",
                    "position": [-0.3338859514721359, -3.929112396378448, -7.207078844568004],
                    "orientation": [-1.0, -0.0, -0.0, -0.0, -1.0, -0.0, 0.0, 0.0, 1.0],
                    "selected": true,
                    "locked": true,
                    "visibility": true,
                    "positionStatus": "defined"
                },
                {
                    "id": "108",
                    "label": "PseudoLandmarks-108",
                    "description": "Semi",
                    "associatedNodeID": "",
                    "position": [-0.15448557896694787, -4.586646042008331, -7.188477617761363],
                    "orientation": [-1.0, -0.0, -0.0, -0.0, -1.0, -0.0, 0.0, 0.0, 1.0],
                    "selected": true,
                    "locked": true,
                    "visibility": true,
                    "positionStatus": "defined"
                },
                {
                    "id": "109",
                    "label": "PseudoLandmarks-109",
                    "description": "Semi",
                    "associatedNodeID": "",
                    "position": [-0.9212028698452438, -4.064500961441925, -7.16777487423109],
                    "orientation": [-1.0, -0.0, -0.0, -0.0, -1.0, -0.0, 0.0, 0.0, 1.0],
                    "selected": true,
                    "locked": true,
                    "visibility": true,
                    "positionStatus": "defined"
                },
                {
                    "id": "110",
                    "label": "PseudoLandmarks-110",
                    "description": "Semi",
                    "associatedNodeID": "",
                    "position": [-0.5538410381802047, -4.000422630448273, -7.1514514031617535],
                    "orientation": [-1.0, -0.0, -0.0, -0.0, -1.0, -0.0, 0.0, 0.0, 1.0],
                    "selected": true,
                    "locked": true,
                    "visibility": true,
                    "positionStatus": "defined"
                },
                {
                    "id": "111",
                    "label": "PseudoLandmarks-111",
                    "description": "Semi",
                    "associatedNodeID": "",
                    "position": [-0.5520384983547653, -4.646674118180206, -7.127091509362925],
                    "orientation": [-1.0, -0.0, -0.0, -0.0, -1.0, -0.0, 0.0, 0.0, 1.0],
                    "selected": true,
                    "locked": true,
                    "visibility": true,
                    "positionStatus": "defined"
                },
                {
                    "id": "112",
                    "label": "PseudoLandmarks-112",
                    "description": "Semi",
                    "associatedNodeID": "",
                    "position": [-1.0731282906063522, -4.254220733780792, -7.122634035608042],
                    "orientation": [-1.0, -0.0, -0.0, -0.0, -1.0, -0.0, 0.0, 0.0, 1.0],
                    "selected": true,
                    "locked": true,
                    "visibility": true,
                    "positionStatus": "defined"
                },
                {
                    "id": "113",
                    "label": "PseudoLandmarks-113",
                    "description": "Semi",
                    "associatedNodeID": "",
                    "position": [-0.7433182911404098, -4.085241470475128, -7.118368441125621],
                    "orientation": [-1.0, -0.0, -0.0, -0.0, -1.0, -0.0, 0.0, 0.0, 1.0],
                    "selected": true,
                    "locked": true,
                    "visibility": true,
                    "positionStatus": "defined"
                },
                {
                    "id": "114",
                    "label": "PseudoLandmarks-114",
                    "description": "Semi",
                    "associatedNodeID": "",
                    "position": [-0.779408045245024, -4.714949188370635, -7.104214769860972],
                    "orientation": [-1.0, -0.0, -0.0, -0.0, -1.0, -0.0, 0.0, 0.0, 1.0],
                    "selected": true,
                    "locked": true,
                    "visibility": true,
                    "positionStatus": "defined"
                },
                {
                    "id": "115",
                    "label": "PseudoLandmarks-115",
                    "description": "Semi",
                    "associatedNodeID": "",
                    "position": [-0.979805632067534, -4.58407608046048, -7.102291018029918],
                    "orientation": [-1.0, -0.0, -0.0, -0.0, -1.0, -0.0, 0.0, 0.0, 1.0],
                    "selected": true,
                    "locked": true,
                    "visibility": true,
                    "positionStatus": "defined"
                },
                {
                    "id": "116",
                    "label": "PseudoLandmarks-116",
                    "description": "Semi",
                    "associatedNodeID": "",
                    "position": [-0.05949547453007353, -4.264388427872588, -7.103525835534801],
                    "orientation": [-1.0, -0.0, -0.0, -0.0, -1.0, -0.0, 0.0, 0.0, 1.0],
                    "selected": true,
                    "locked": true,
                    "visibility": true,
                    "positionStatus": "defined"
                },
                {
                    "id": "117",
                    "label": "PseudoLandmarks-117",
                    "description": "Semi",
                    "associatedNodeID": "",
                    "position": [-0.06090117855152733, -4.0678125001382135, -7.102448565026988],
                    "orientation": [-1.0, -0.0, -0.0, -0.0, -1.0, -0.0, 0.0, 0.0, 1.0],
                    "selected": true,
                    "locked": true,
                    "visibility": true,
                    "positionStatus": "defined"
                },
                {
                    "id": "118",
                    "label": "PseudoLandmarks-118",
                    "description": "Semi",
                    "associatedNodeID": "",
                    "position": [-0.12586597347787265, -4.44525543226712, -7.074988466760386],
                    "orientation": [-1.0, -0.0, -0.0, -0.0, -1.0, -0.0, 0.0, 0.0, 1.0],
                    "selected": true,
                    "locked": true,
                    "visibility": true,
                    "positionStatus": "defined"
                },
                {
                    "id": "119",
                    "label": "PseudoLandmarks-119",
                    "description": "Semi",
                    "associatedNodeID": "",
                    "position": [-0.9018892483242478, -4.236480484147003, -7.060394960901012],
                    "orientation": [-1.0, -0.0, -0.0, -0.0, -1.0, -0.0, 0.0, 0.0, 1.0],
                    "selected": true,
                    "locked": true,
                    "visibility": true,
                    "positionStatus": "defined"
                },
                {
                    "id": "120",
                    "label": "PseudoLandmarks-120",
                    "description": "Semi",
                    "associatedNodeID": "",
                    "position": [-0.3981628851421798, -4.042679367203643, -7.0560648980348],
                    "orientation": [-1.0, -0.0, -0.0, -0.0, -1.0, -0.0, 0.0, 0.0, 1.0],
                    "selected": true,
                    "locked": true,
                    "visibility": true,
                    "positionStatus": "defined"
                },
                {
                    "id": "121",
                    "label": "PseudoLandmarks-121",
                    "description": "Semi",
                    "associatedNodeID": "",
                    "position": [-0.3110391096600021, -4.610751114029815, -7.040706545373668],
                    "orientation": [-1.0, -0.0, -0.0, -0.0, -1.0, -0.0, 0.0, 0.0, 1.0],
                    "selected": true,
                    "locked": true,
                    "visibility": true,
                    "positionStatus": "defined"
                },
                {
                    "id": "122",
                    "label": "PseudoLandmarks-122",
                    "description": "Semi",
                    "associatedNodeID": "",
                    "position": [-1.0215926842220748, -4.413690338272979, -7.050862032434215],
                    "orientation": [-1.0, -0.0, -0.0, -0.0, -1.0, -0.0, 0.0, 0.0, 1.0],
                    "selected": true,
                    "locked": true,
                    "visibility": true,
                    "positionStatus": "defined"
                },
                {
                    "id": "123",
                    "label": "PseudoLandmarks-123",
                    "description": "Semi",
                    "associatedNodeID": "",
                    "position": [-0.5937062458523239, -4.1285115815591125, -7.012119967004527],
                    "orientation": [-1.0, -0.0, -0.0, -0.0, -1.0, -0.0, 0.0, 0.0, 1.0],
                    "selected": true,
                    "locked": true,
                    "visibility": true,
                    "positionStatus": "defined"
                },
                {
                    "id": "124",
                    "label": "PseudoLandmarks-124",
                    "description": "Semi",
                    "associatedNodeID": "",
                    "position": [-0.8225296215542282, -4.557977447647979, -6.99222326900648],
                    "orientation": [-1.0, -0.0, -0.0, -0.0, -1.0, -0.0, 0.0, 0.0, 1.0],
                    "selected": true,
                    "locked": true,
                    "visibility": true,
                    "positionStatus": "defined"
                },
                {
                    "id": "125",
                    "label": "PseudoLandmarks-125",
                    "description": "Semi",
                    "associatedNodeID": "",
                    "position": [-0.22743666930279385, -4.065397415299347, -6.994260317346324],
                    "orientation": [-1.0, -0.0, -0.0, -0.0, -1.0, -0.0, 0.0, 0.0, 1.0],
                    "selected": true,
                    "locked": true,
                    "visibility": true,
                    "positionStatus": "defined"
                },
                {
                    "id": "126",
                    "label": "PseudoLandmarks-126",
                    "description": "Semi",
                    "associatedNodeID": "",
                    "position": [-0.6679256157406296, -4.662962494034698, -6.96810331966566],
                    "orientation": [-1.0, -0.0, -0.0, -0.0, -1.0, -0.0, 0.0, 0.0, 1.0],
                    "selected": true,
                    "locked": true,
                    "visibility": true,
                    "positionStatus": "defined"
                },
                {
                    "id": "127",
                    "label": "PseudoLandmarks-127",
                    "description": "Semi",
                    "associatedNodeID": "",
                    "position": [-0.7354750351437057, -4.248640594620635, -6.979821688195933],
                    "orientation": [-1.0, -0.0, -0.0, -0.0, -1.0, -0.0, 0.0, 0.0, 1.0],
                    "selected": true,
                    "locked": true,
                    "visibility": true,
                    "positionStatus": "defined"
                },
                {
                    "id": "128",
                    "label": "PseudoLandmarks-128",
                    "description": "Semi",
                    "associatedNodeID": "",
                    "position": [-0.4699136213787521, -4.654910431046416, -6.958096224328746],
                    "orientation": [-1.0, -0.0, -0.0, -0.0, -1.0, -0.0, 0.0, 0.0, 1.0],
                    "selected": true,
                    "locked": true,
                    "visibility": true,
                    "positionStatus": "defined"
                },
                {
                    "id": "129",
                    "label": "PseudoLandmarks-129",
                    "description": "Semi",
                    "associatedNodeID": "",
                    "position": [-0.1656563685663665, -4.311895904679229, -6.950139147302378],
                    "orientation": [-1.0, -0.0, -0.0, -0.0, -1.0, -0.0, 0.0, 0.0, 1.0],
                    "selected": true,
                    "locked": true,
                    "visibility": true,
                    "positionStatus": "defined"
                },
                {
                    "id": "130",
                    "label": "PseudoLandmarks-130",
                    "description": "Semi",
                    "associatedNodeID": "",
                    "position": [-0.21986796422085417, -4.527328643937042, -6.901298052331676],
                    "orientation": [-1.0, -0.0, -0.0, -0.0, -1.0, -0.0, 0.0, 0.0, 1.0],
                    "selected": true,
                    "locked": true,
                    "visibility": true,
                    "positionStatus": "defined"
                },
                {
                    "id": "131",
                    "label": "PseudoLandmarks-131",
                    "description": "Semi",
                    "associatedNodeID": "",
                    "position": [-0.4454593615063156, -4.174594268937041, -6.912388903161753],
                    "orientation": [-1.0, -0.0, -0.0, -0.0, -1.0, -0.0, 0.0, 0.0, 1.0],
                    "selected": true,
                    "locked": true,
                    "visibility": true,
                    "positionStatus": "defined"
                },
                {
                    "id": "132",
                    "label": "PseudoLandmarks-132",
                    "description": "Semi",
                    "associatedNodeID": "",
                    "position": [-0.7421808914669479, -4.420586929459502, -6.898163515588512],
                    "orientation": [-1.0, -0.0, -0.0, -0.0, -1.0, -0.0, 0.0, 0.0, 1.0],
                    "selected": true,
                    "locked": true,
                    "visibility": true,
                    "positionStatus": "defined"
                },
                {
                    "id": "133",
                    "label": "PseudoLandmarks-133",
                    "description": "Semi",
                    "associatedNodeID": "",
                    "position": [-0.33171822590908656, -4.674238357682159, -6.834377962609996],
                    "orientation": [-1.0, -0.0, -0.0, -0.0, -1.0, -0.0, 0.0, 0.0, 1.0],
                    "selected": true,
                    "locked": true,
                    "visibility": true,
                    "positionStatus": "defined"
                },
                {
                    "id": "134",
                    "label": "PseudoLandmarks-134",
                    "description": "Semi",
                    "associatedNodeID": "",
                    "position": [-0.5916828827389206, -4.325357208390167, -6.841112810632457],
                    "orientation": [-1.0, -0.0, -0.0, -0.0, -1.0, -0.0, 0.0, 0.0, 1.0],
                    "selected": true,
                    "locked": true,
                    "visibility": true,
                    "positionStatus": "defined"
                },
                {
                    "id": "135",
                    "label": "PseudoLandmarks-135",
                    "description": "Semi",
                    "associatedNodeID": "",
                    "position": [-0.31892916722378384, -4.283291778702667, -6.8241099419801134],
                    "orientation": [-1.0, -0.0, -0.0, -0.0, -1.0, -0.0, 0.0, 0.0, 1.0],
                    "selected": true,
                    "locked": true,
                    "visibility": true,
                    "positionStatus": "defined"
                },
                {
                    "id": "136",
                    "label": "PseudoLandmarks-136",
                    "description": "Semi",
                    "associatedNodeID": "",
                    "position": [-0.5864236073025192, -4.703537521500518, -6.808360201379527],
                    "orientation": [-1.0, -0.0, -0.0, -0.0, -1.0, -0.0, 0.0, 0.0, 1.0],
                    "selected": true,
                    "locked": true,
                    "visibility": true,
                    "positionStatus": "defined"
                },
                {
                    "id": "137",
                    "label": "PseudoLandmarks-137",
                    "description": "Semi",
                    "associatedNodeID": "",
                    "position": [-0.611318846178862, -4.522786102433136, -6.789851671716441],
                    "orientation": [-1.0, -0.0, -0.0, -0.0, -1.0, -0.0, 0.0, 0.0, 1.0],
                    "selected": true,
                    "locked": true,
                    "visibility": true,
                    "positionStatus": "defined"
                },
                {
                    "id": "138",
                    "label": "PseudoLandmarks-138",
                    "description": "Semi",
                    "associatedNodeID": "",
                    "position": [-0.3456767038830246, -4.504024658341339, -6.761269289514293],
                    "orientation": [-1.0, -0.0, -0.0, -0.0, -1.0, -0.0, 0.0, 0.0, 1.0],
                    "selected": true,
                    "locked": true,
                    "visibility": true,
                    "positionStatus": "defined"
                }
            ],
            "measurements": [],
            "display": {
                "visibility": false,
                "opacity": 1.0,
                "color": [1.0, 0.0, 1.0],
                "selectedColor": [0.7176470588235294, 0.611764705882353, 0.8627450980392157],
                "activeColor": [0.4, 1.0, 0.0],
                "propertiesLabelVisibility": false,
                "pointLabelsVisibility": false,
                "textScale": 3.0,
                "glyphType": "Sphere3D",
                "glyphScale": 3.0,
                "glyphSize": 5.0,
                "useGlyphScale": true,
                "sliceProjection": false,
                "sliceProjectionUseFiducialColor": true,
                "sliceProjectionOutlinedBehindSlicePlane": false,
                "sliceProjectionColor": [1.0, 1.0, 1.0],
                "sliceProjectionOpacity": 0.6,
                "lineThickness": 0.2,
                "lineColorFadingStart": 1.0,
                "lineColorFadingEnd": 10.0,
                "lineColorFadingSaturation": 1.0,
                "lineColorFadingHueOffset": 0.0,
                "handlesInteractive": false,
                "translationHandleVisibility": true,
                "rotationHandleVisibility": true,
                "scaleHandleVisibility": true,
                "interactionHandleScale": 3.0,
                "snapMode": "toVisibleSurface"
            }
        }
    ]
}